setup.py
guessing_game/__init__.py
guessing_game/guess.py
guessing_game/guessing_game.py
guessing_game.egg-info/PKG-INFO
guessing_game.egg-info/SOURCES.txt
guessing_game.egg-info/dependency_links.txt
guessing_game.egg-info/not-zip-safe
guessing_game.egg-info/top_level.txt