Metadata-Version: 1.0
Name: guessing-game
Version: 0.0.0
Summary: Guessing Game
Home-page: UNKNOWN
Author: UNKNOWN
Author-email: UNKNOWN
License: UNKNOWN
Platform: UNKNOWN
